grayCode.v
module grayCode(out, clk, res);
    output [1:0]out;
    input clk, res;
    wire [1:0]q;

    counter c(q, clk, res);
    gray_encoder g(out, q);
endmodule

module gray_encoder(out, in);
    output [1:0]out;
    input [1:0]in;

    and (out[0], in[0], in[1]);
    xor (out[1], in[0], in[1]);
endmodule

module counter(q, clk, res);
    output [1:0]q;
    input clk, res;

    T_FF t0(q[0], 1'b1, clk, res);
    T_FF t1(q[1], q[0], clk, res);
endmodule

module T_FF(q, t, clk, res);
    output q;
    input t, clk, res;
    wire d;

    xor (d, q, t);
    D_FF dff(q, d, clk, res);
endmodule

module D_FF(q, d, clk, res);
    output q;
    input d, clk, res;
    reg q;
    always @(posedge res or negedge clk) begin
        if (res == 1'b1) begin
            q <= 1'b0;
        end else begin
            q <= d;
        end
    end
endmodule

00  00
01  01
10  11
11  10

grayCodeStimulus.v
module grayCodeStimulus;
    reg clk, res;
    wire [1:0]out;

    grayCode g(out, clk, res);
    initial begin
        $dumpfile("grayCode.vcd");
        $dumpvars(0, grayCodeStimulus);
        clk = 1'b0;
    end
    always #5 clk = ~clk;
    initial #100 $finish;
    initial begin
        res = 1'b1;
        #10 res = 1'b0;
        #50 res = 1'b1;
        #10 res = 1'b0;
    end
    initial $monitor("out=%b", out);
endmodule

grayCode.vcd
$date
	Tue Oct 03 14:29:32 2023
$end
$version
	Icarus Verilog
$end
$timescale
	1s
$end
$scope module grayCodeStimulus $end
$var wire 2 ! out [1:0] $end
$var reg 1 " clk $end
$var reg 1 # res $end
$scope module g $end
$var wire 1 " clk $end
$var wire 1 # res $end
$var wire 2 $ q [1:0] $end
$var wire 2 % out [1:0] $end
$scope module c $end
$var wire 1 " clk $end
$var wire 1 # res $end
$var wire 2 & q [1:0] $end
$scope module t0 $end
$var wire 1 " clk $end
$var wire 1 ' d $end
$var wire 1 # res $end
$var wire 1 ( t $end
$var wire 1 ) q $end
$scope module dff $end
$var wire 1 " clk $end
$var wire 1 ' d $end
$var wire 1 # res $end
$var reg 1 ) q $end
$upscope $end
$upscope $end
$scope module t1 $end
$var wire 1 " clk $end
$var wire 1 * d $end
$var wire 1 # res $end
$var wire 1 + t $end
$var wire 1 , q $end
$scope module dff $end
$var wire 1 " clk $end
$var wire 1 * d $end
$var wire 1 # res $end
$var reg 1 , q $end
$upscope $end
$upscope $end
$upscope $end
$scope module g $end
$var wire 2 - in [1:0] $end
$var wire 2 . out [1:0] $end
$upscope $end
$upscope $end
$upscope $end
$enddefinitions $end
$comment Show the parameter values. $end
$dumpall
$end
#0
$dumpvars
b0 .
b0 -
0,
0+
0*
0)
1(
1'
b0 &
b0 %
b0 $
1#
0"
b0 !
$end
#5
1"
#10
1*
b10 !
b10 %
b10 .
0'
1+
b1 $
b1 &
b1 -
1)
0"
0#
#15
1"
#20
1'
0+
1*
0)
b10 $
b10 &
b10 -
1,
0"
#25
1"
#30
0*
b1 !
b1 %
b1 .
0'
1+
b11 $
b11 &
b11 -
1)
0"
#35
1"
#40
b0 !
b0 %
b0 .
1'
0+
0*
0)
b0 $
b0 &
b0 -
0,
0"
#45
1"
#50
1*
b10 !
b10 %
b10 .
0'
1+
b1 $
b1 &
b1 -
1)
0"
#55
1"
#60
0*
b0 !
b0 %
b0 .
1'
0+
b0 $
b0 &
b0 -
0)
0"
1#
#65
1"
#70
1*
b10 !
b10 %
b10 .
0'
1+
b1 $
b1 &
b1 -
1)
0"
0#
#75
1"
#80
1'
0+
1*
0)
b10 $
b10 &
b10 -
1,
0"
#85
1"
#90
0*
b1 !
b1 %
b1 .
0'
1+
b11 $
b11 &
b11 -
1)
0"
#95
1"
#100
b0 !
b0 %
b0 .
1'
0+
0*
0)
b0 $
b0 &
b0 -
0,
0"
